README.md
setup.py
CodePay.egg-info/PKG-INFO
CodePay.egg-info/SOURCES.txt
CodePay.egg-info/dependency_links.txt
CodePay.egg-info/top_level.txt
CodePay_Python/__init__.py
CodePay_Python/codePay.py
test/test_codepay.py