Metadata-Version: 2.1
Name: CodePay
Version: 1.1
Summary: codepy python library
Home-page: https://github.com/Fly744055970/codepay_python
Author: LCF
Author-email: 1019197976@qq.com
License: Apache 2.0
Keywords: codepay,codepay_python
Platform: UNKNOWN
Classifier: Development Status :: 3 - Alpha
Classifier: Intended Audience :: Developers
Classifier: Programming Language :: Python :: 3
Classifier: Programming Language :: Python :: 3.7
Classifier: Programming Language :: Python :: 3.8
Classifier: Programming Language :: Python :: 3.9
Classifier: Programming Language :: Python :: 3.10
Classifier: Programming Language :: Python :: 3 :: Only
Classifier: License :: OSI Approved :: MIT License
Classifier: Operating System :: OS Independent
